HypixelWrapper/Test.py
HypixelWrapper/__init__.py
HypixelWrapper/errors.py
HypixelWrapper/guild.py
HypixelWrapper/guildldb.py
HypixelWrapper/key.py
HypixelWrapper/player.py
HypixelWrapper/utils.py
HypixelWrapper/vars.py
HypixelWrapper-0.0.1.dist-info/LICENSE
HypixelWrapper-0.0.1.dist-info/METADATA
HypixelWrapper-0.0.1.dist-info/WHEEL
HypixelWrapper-0.0.1.dist-info/top_level.txt
HypixelWrapper-0.0.1.dist-info/RECORD
